application/__init__.py
application/forms.py
application/models.py
application/services.py
application/views.py
application/tests/__init__.py
application/tests/conftest.py
application/tests/models_test.py
application/tests/views_test.py
DepartmnetHelper-1.0.0.dist-info/METADATA
DepartmnetHelper-1.0.0.dist-info/WHEEL
DepartmnetHelper-1.0.0.dist-info/top_level.txt
DepartmnetHelper-1.0.0.dist-info/RECORD
