Metadata-Version: 2.1
Name: DepartmnetHelper
Version: 1.0.0
Summary: UNKNOWN
Home-page: UNKNOWN
Author: YuraKulchytskiy
Author-email: kulchytskiyyura@gmail.com
License: UNKNOWN
Platform: UNKNOWN
Requires-Dist: pytest
Requires-Dist: flask
Requires-Dist: wtforms
Requires-Dist: flask-sqlalchemy
Requires-Dist: flask-migrate
